sae_vis/__init__.py
sae_vis/data_config_classes.py
sae_vis/data_fetching_fns.py
sae_vis/data_storing_fns.py
sae_vis/demos/demo.py
sae_vis/demos/demo_feature_vis.html
sae_vis/demos/demo_feature_vis_attn2l.html
sae_vis/demos/demo_feature_vis_custom.html
sae_vis/demos/demo_othello_vis.html
sae_vis/demos/demo_prompt_vis.html
sae_vis/init.js
sae_vis/model_fns.py
sae_vis/style.css
sae_vis/utils_fns.py
sae_vis-0.3.6.dist-info/LICENSE
sae_vis-0.3.6.dist-info/METADATA
sae_vis-0.3.6.dist-info/WHEEL
sae_vis-0.3.6.dist-info/RECORD
