Metadata-Version: 2.1
Name: sae-vis
Version: 0.3.6
Summary: Open-source SAE visualizer, based on Anthropic's published visualizer.
License: MIT
Author: Callum McDougall
Author-email: cal.s.mcdougall@gmail.com
Requires-Python: >=3.10,<4.0
Classifier: License :: OSI Approved :: MIT License
Classifier: Programming Language :: Python :: 3
Classifier: Programming Language :: Python :: 3.10
Classifier: Programming Language :: Python :: 3.11
Classifier: Programming Language :: Python :: 3.12
Requires-Dist: dataclasses-json (>=0.6.4,<0.7.0)
Requires-Dist: datasets (>=2.0.0,<3.0.0)
Requires-Dist: eindex-callum (>=0.1.0,<0.2.0)
Requires-Dist: einops (>=0.7.0,<0.8.0)
Requires-Dist: jaxtyping (>=0.2.28,<0.3.0)
Requires-Dist: matplotlib (>=3.8.4,<4.0.0)
Requires-Dist: rich (>=13.7.1,<14.0.0)
Requires-Dist: torch (>=2.0.0,<3.0.0)
Requires-Dist: transformer-lens (>=2.0.0,<3.0.0)
